odoo/addons/invader_payment/README.rst
odoo/addons/invader_payment/__init__.py
odoo/addons/invader_payment/__manifest__.py
odoo/addons/invader_payment/i18n/invader_payment.pot
odoo/addons/invader_payment/models/__init__.py
odoo/addons/invader_payment/models/invader_payable.py
odoo/addons/invader_payment/models/payment_transaction.py
odoo/addons/invader_payment/readme/CONTRIBUTORS.rst
odoo/addons/invader_payment/readme/DESCRIPTION.rst
odoo/addons/invader_payment/services/__init__.py
odoo/addons/invader_payment/services/invader_payment_service.py
odoo/addons/invader_payment/static/description/index.html
odoo14_addon_invader_payment-14.0.1.0.5.dist-info/METADATA
odoo14_addon_invader_payment-14.0.1.0.5.dist-info/WHEEL
odoo14_addon_invader_payment-14.0.1.0.5.dist-info/top_level.txt
odoo14_addon_invader_payment-14.0.1.0.5.dist-info/RECORD
